bert_slot_tokenizer/__init__.py
bert_slot_tokenizer/main.py
bert_slot_tokenizer/bert_tokenizer/__init__.py
bert_slot_tokenizer/bert_tokenizer/tokenization.py
bert_slot_tokenizer-0.3.0.dist-info/LICENSE
bert_slot_tokenizer-0.3.0.dist-info/METADATA
bert_slot_tokenizer-0.3.0.dist-info/WHEEL
bert_slot_tokenizer-0.3.0.dist-info/entry_points.txt
bert_slot_tokenizer-0.3.0.dist-info/top_level.txt
bert_slot_tokenizer-0.3.0.dist-info/RECORD
