Metadata-Version: 2.1
Name: bert-slot-tokenizer
Version: 0.3.0
Summary: A tool for converting raw text to slot
Home-page: https://github.com/DevRoss/bert-slot-tokenizer
Author: DevRoss
Author-email: devross1997@gmail.com
License: License :: OSI Approved :: Apache Software License
Keywords: bert_slot_tokenizer,bert,slot filling
Platform: UNKNOWN
Classifier: Development Status :: 4 - Beta
Classifier: Programming Language :: Python :: 2
Classifier: Programming Language :: Python :: 3
Classifier: Operating System :: OS Independent
Classifier: Programming Language :: Python :: Implementation :: PyPy
Requires-Python: >=2.7
